pycheops/VERSION
pycheops/__init__.py
pycheops/calculate_coefficients.py
pycheops/combine.py
pycheops/constants.py
pycheops/core.py
pycheops/dataset.py
pycheops/funcs.py
pycheops/instrument.py
pycheops/ld.py
pycheops/make_xml_files.py
pycheops/models.py
pycheops/multivisit.py
pycheops/planetproperties.py
pycheops/quantities.py
pycheops/starproperties.py
pycheops/utils.py
pycheops/data/BrightStarCat/ReadMe
pycheops/data/BrightStarCat/bscat.fits
pycheops/data/EEM_dwarf_UBVIJHK_colors_Teff/EEM_dwarf_UBVIJHK_colors_Teff.txt
pycheops/data/cdspyreadme/ReadMe.template
pycheops/data/instrument/CHEOPS_IT_PSFwhite_CH_TU2018-01-01.txt
pycheops/data/instrument/C_G_Teff.csv
pycheops/data/instrument/VisibilityTable12.csv
pycheops/data/instrument/VisibilityTable6.csv
pycheops/data/instrument/cadence.csv
pycheops/data/limbdarkening/power2.dat
pycheops/data/models/aa9321-07_table4.csv
pycheops/data/models/apj522803t2_mrt.txt
pycheops/data/response_functions/response_functions.fits
pycheops/examples/Notebooks/HAT-P2_rv.csv
pycheops/examples/Notebooks/HD_17156.ipynb
pycheops/examples/Notebooks/J0113+31_J-band.csv
pycheops/examples/Notebooks/KELT-11b-tutorial.ipynb
pycheops/examples/Notebooks/PlotPlanetPosition.ipynb
pycheops/examples/Notebooks/TESS_HD211970_radius_limit.ipynb
pycheops/examples/Notebooks/TESS_fit_TOI562.1.ipynb
pycheops/examples/Notebooks/TestEclipseModel.ipynb
pycheops/examples/Notebooks/TestPriors.ipynb
pycheops/examples/Notebooks/TestRVModel.ipynb
pycheops/examples/Notebooks/TestReflectionModel.ipynb
pycheops/examples/Notebooks/TestThermalPhaseModel.ipynb
pycheops/examples/Notebooks/TestTransitModel.ipynb
pycheops/examples/Notebooks/TestTransitModel1Spot.ipynb
pycheops/examples/Notebooks/TestTransitModel2Spot.ipynb
pycheops/examples/Notebooks/Test_scaled_transit_fit.ipynb
pycheops/examples/Notebooks/Test_transit_noise.ipynb
pycheops/examples/Notebooks/WASP-189.ipynb
pycheops/examples/Notebooks/extra_decorr_vectors.ipynb
pycheops/examples/Notebooks/massradius.ipynb
pycheops-1.1.25.dist-info/licenses/LICENSE
pycheops-1.1.25.dist-info/METADATA
pycheops-1.1.25.dist-info/WHEEL
pycheops-1.1.25.dist-info/entry_points.txt
pycheops-1.1.25.dist-info/top_level.txt
pycheops-1.1.25.dist-info/RECORD
