Metadata-Version: 2.4
Name: pycheops
Version: 1.1.25
Summary: CHEOPS light curve analysis software
Home-page: http://cheops.unibe.ch/
Author: CHEOPS Science Team
Author-email: p.maxted@keele.ac.uk
License: GNU GPLv3
Keywords: astronomy
Classifier: Development Status :: 1 - Planning
Classifier: Intended Audience :: Science/Research
Classifier: Topic :: Scientific/Engineering
Classifier: License :: OSI Approved :: GNU General Public License v3 (GPLv3)
Classifier: Programming Language :: Python :: 3.6
License-File: LICENSE
Requires-Dist: numpy>=1.17.2
Requires-Dist: scipy
Requires-Dist: astropy>=3.2.2
Requires-Dist: emcee>=3.0.0
Requires-Dist: astroquery
Requires-Dist: numba>=0.44.1
Requires-Dist: lmfit>=0.9.14
Requires-Dist: corner
Requires-Dist: photutils
Requires-Dist: matplotlib>3.2
Requires-Dist: celerite2
Requires-Dist: cdspyreadme
Requires-Dist: dace-query>=2.0.0
Requires-Dist: IPython
Requires-Dist: tqdm
Dynamic: author
Dynamic: author-email
Dynamic: classifier
Dynamic: description
Dynamic: home-page
Dynamic: keywords
Dynamic: license
Dynamic: license-file
Dynamic: requires-dist
Dynamic: summary
